pydiverse/common/__init__.py
pydiverse/common/dtypes.py
pydiverse/common/py.typed
pydiverse/common/testing.py
pydiverse/common/version.py
pydiverse/common/errors/__init__.py
pydiverse/common/util/__init__.py
pydiverse/common/util/computation_tracing.py
pydiverse/common/util/deep_map.py
pydiverse/common/util/deep_merge.py
pydiverse/common/util/disposable.py
pydiverse/common/util/hashing.py
pydiverse/common/util/import_.py
pydiverse/common/util/structlog.py
pydiverse_common-0.4.4.dist-info/METADATA
pydiverse_common-0.4.4.dist-info/WHEEL
pydiverse_common-0.4.4.dist-info/licenses/LICENSE
pydiverse_common-0.4.4.dist-info/RECORD
