Metadata-Version: 2.4
Name: pydiverse-common
Version: 0.4.4
Summary: Common functionality shared between pydiverse libraries
Author: QuantCo, Inc.
Author-email: Martin Trautmann <windiana@users.sf.net>, Finn Rudolph <finn.rudolph@t-online.de>
License: BSD 3-Clause License
License-File: LICENSE
Classifier: Development Status :: 5 - Production/Stable
Classifier: Intended Audience :: Developers
Classifier: Intended Audience :: Science/Research
Classifier: License :: OSI Approved :: BSD License
Classifier: Programming Language :: Python :: 3
Classifier: Programming Language :: Python :: 3.11
Classifier: Programming Language :: Python :: 3.12
Classifier: Programming Language :: Python :: 3.13
Classifier: Programming Language :: Python :: 3.14
Classifier: Programming Language :: SQL
Classifier: Topic :: Database
Classifier: Topic :: Scientific/Engineering
Classifier: Topic :: Software Development
Requires-Python: <3.15.0a0,>=3.11.14
Requires-Dist: python-box<8,>=7.3.2
